websauna.system-1.0a8-py3.6-nspkg.pth
websauna/system/__init__.py
websauna/system/admin/__init__.py
websauna/system/admin/admin.py
websauna/system/admin/events.py
websauna/system/admin/filters.py
websauna/system/admin/interfaces.py
websauna/system/admin/menu.py
websauna/system/admin/modeladmin.py
websauna/system/admin/subscribers.py
websauna/system/admin/utils.py
websauna/system/admin/views.py
websauna/system/admin/templates/admin/admin.html
websauna/system/admin/templates/admin/base.html
websauna/system/admin/templates/admin/base_panel.html
websauna/system/admin/templates/admin/breadcrumbs.html
websauna/system/admin/templates/admin/model_panel.html
websauna/system/admin/templates/admin/menu/entry.html
websauna/system/admin/templates/admin/menu/navbar.html
websauna/system/admin/templates/admin/menu/submenu.html
websauna/system/auth/__init__.py
websauna/system/auth/authentication.py
websauna/system/auth/policy.py
websauna/system/auth/principals.py
websauna/system/auth/subscribers.py
websauna/system/auth/tweens.py
websauna/system/compat/__init__.py
websauna/system/compat/typing.py
websauna/system/conf/base.ini
websauna/system/conf/development.ini
websauna/system/conf/production.ini
websauna/system/conf/secrets.ini
websauna/system/conf/test-secrets.ini
websauna/system/conf/test-sqlite.ini
websauna/system/conf/test.ini
websauna/system/conf/travis.ini
websauna/system/core/__init__.py
websauna/system/core/breadcrumbs.py
websauna/system/core/events.py
websauna/system/core/interfaces.py
websauna/system/core/loggingcapture.py
websauna/system/core/messages.py
websauna/system/core/panel.py
websauna/system/core/redis.py
websauna/system/core/render.py
websauna/system/core/root.py
websauna/system/core/route.py
websauna/system/core/session.py
websauna/system/core/simpleroute.py
websauna/system/core/sitemap.py
websauna/system/core/templatecontext.py
websauna/system/core/traversal.py
websauna/system/core/utils.py
websauna.system-1.0a8.dist-info/DESCRIPTION.rst
websauna.system-1.0a8.dist-info/METADATA
websauna.system-1.0a8.dist-info/RECORD
websauna.system-1.0a8.dist-info/WHEEL
websauna.system-1.0a8.dist-info/entry_points.txt
websauna.system-1.0a8.dist-info/metadata.json
websauna.system-1.0a8.dist-info/namespace_packages.txt
websauna.system-1.0a8.dist-info/top_level.txt
