Metadata-Version: 2.0
Name: websauna.system
Version: 1.0a8
Summary: websauna.system is the core component of Websauna framework.
Home-page: https://websauna.org
Author: Mikko Ohtamaa
Author-email: mikko@opensourcehacker.com
License: MIT
Keywords: sqlalchemy postgresql pyramid pytest websauna
Platform: UNKNOWN
Classifier: Development Status :: 3 - Alpha
Classifier: Framework :: Pyramid
Classifier: Intended Audience :: Developers
Classifier: License :: OSI Approved :: MIT License
Classifier: Programming Language :: Python :: 3
Classifier: Programming Language :: Python :: 3.5
Classifier: Programming Language :: Python :: 3.6
Classifier: Programming Language :: Python :: Implementation :: CPython
Classifier: Topic :: Internet :: WWW/HTTP
Classifier: Topic :: Internet :: WWW/HTTP :: Dynamic Content
Classifier: Topic :: Internet :: WWW/HTTP :: WSGI :: Application
Classifier: Topic :: Internet :: WWW/HTTP :: WSGI
Classifier: Topic :: Software Development :: Libraries :: Application Frameworks
Requires-Python: >=3.5.2,<3.8
Requires-Dist: websauna.utils
Requires-Dist: pyramid (>=1.9)
Requires-Dist: waitress
Requires-Dist: pyramid-redis-sessions
Requires-Dist: pyramid-layout
Requires-Dist: deform (>=2.0.4)
Requires-Dist: pyramid-debugtoolbar
Requires-Dist: pyramid-jinja2
Requires-Dist: arrow
Requires-Dist: pytz
Requires-Dist: alembic
Requires-Dist: colanderalchemy
Requires-Dist: psycopg2
Requires-Dist: pyramid-retry
Requires-Dist: pyramid-tm
Requires-Dist: sqlalchemy
Requires-Dist: sqlalchemy-utils
Requires-Dist: zope.sqlalchemy
Requires-Dist: argon2-cffi
Requires-Dist: authomatic
Requires-Dist: pyramid-mailer
Requires-Dist: premailer
Requires-Dist: rainbow-logging-handler
Requires-Dist: python-slugify
Provides-Extra: celery
Requires-Dist: celery[redis] (>=4.1.0); extra == 'celery'
Provides-Extra: dev
Requires-Dist: ruamel.yaml; extra == 'dev'
Requires-Dist: setuptools-git; extra == 'dev'
Requires-Dist: pyroma (==2.2); extra == 'dev'
Requires-Dist: sphinx (>=1.6.1); extra == 'dev'
Requires-Dist: sphinx-autodoc-typehints; extra == 'dev'
Requires-Dist: sphinx-rtd-theme; extra == 'dev'
Requires-Dist: sphinxcontrib-zopeext; extra == 'dev'
Requires-Dist: zest.releaser[recommended]; extra == 'dev'
Provides-Extra: notebook
Requires-Dist: ipython[notebook] (<5.2); extra == 'notebook'
Requires-Dist: pyramid-notebook (>=0.2.1); extra == 'notebook'
Requires-Dist: PasteDeploy; extra == 'notebook'
Provides-Extra: test
Requires-Dist: celery; extra == 'test'
Requires-Dist: websauna.tests; extra == 'test'
Requires-Dist: cookiecutter; extra == 'test'
Requires-Dist: codecov; extra == 'test'
Requires-Dist: flake8; extra == 'test'
Requires-Dist: pytest (>=3.0); extra == 'test'
Requires-Dist: pytest-runner; extra == 'test'
Requires-Dist: coverage; extra == 'test'
Requires-Dist: flaky; extra == 'test'
Requires-Dist: isort; extra == 'test'
Requires-Dist: pytest-cov; extra == 'test'
Requires-Dist: pytest-runner; extra == 'test'
Requires-Dist: pytest-splinter; extra == 'test'
Requires-Dist: pytest-timeout; extra == 'test'
Requires-Dist: webtest; extra == 'test'
Provides-Extra: utils
Requires-Dist: pgcli; extra == 'utils'
